ohms_law_jh/__init__.py
ohms_law_jh/calc.py
ohms_law_jh-0.1.3.dist-info/LICENSE
ohms_law_jh-0.1.3.dist-info/METADATA
ohms_law_jh-0.1.3.dist-info/WHEEL
ohms_law_jh-0.1.3.dist-info/top_level.txt
ohms_law_jh-0.1.3.dist-info/RECORD
